第六七章-深度学习处理器运算器设计实验/dlp_ex_student/src/inner_product_4x16.v
module inner_product_4x16 (
    input wire clk,
    input wire reset,
    input wire enable,
    input wire signed [15:0] activations [0:3],
    input wire signed [15:0] weights [0:3],
    output reg signed [31:0] result
);
    // 输入寄存器
    reg signed [15:0] activations_reg [0:3];
    reg signed [15:0] weights_reg [0:3];
    
    // 组合逻辑部分
    wire signed [31:0] dot_product = 
        (activations_reg[0] * weights_reg[0]) +
        (activations_reg[1] * weights_reg[1]) +
        (activations_reg[2] * weights_reg[2]) +
        (activations_reg[3] * weights_reg[3]);
    
    // 寄存器更新逻辑
    integer i;
    always @(posedge clk) begin
        if (reset) begin
            for (i = 0; i < 4; i = i + 1) begin
                activations_reg[i] <= 16'd0;
                weights_reg[i] <= 16'd0;
            end
            result <= 32'd0;
        end else if (enable) begin
            for (i = 0; i < 4; i = i + 1) begin
                activations_reg[i] <= activations[i];
                weights_reg[i] <= weights[i];
            end
            result <= dot_product;
        end
    end
endmodule

第六七章-深度学习处理器运算器设计实验/dlp_ex_student/src/matrix_vector_mult_4x4x16.v
module matrix_vector_mult_4x4x16 (
    input wire clk,
    input wire reset,
    input wire enable,
    input wire signed [15:0] activations [0:3],
    input wire signed [15:0] weights [0:3][0:3],
    output wire signed [31:0] results [0:3]
);

inner_product_4x16 ipu0 (
    .clk(clk),
    .reset(reset),
    .enable(enable),
    .activations(activations),
    .weights(weights[0]),
    .result(results[0])
);
inner_product_4x16 ipu1 (
    .clk(clk),
    .reset(reset),
    .enable(enable),
    .activations(activations),
    .weights(weights[1]),
    .result(results[1])
);
inner_product_4x16 ipu2 (
    .clk(clk),
    .reset(reset),
    .enable(enable),
    .activations(activations),
    .weights(weights[2]),
    .result(results[2])
);
inner_product_4x16 ipu3 (
    .clk(clk),
    .reset(reset),
    .enable(enable),
    .activations(activations),
    .weights(weights[3]),
    .result(results[3])
);

endmodule

第六七章-深度学习处理器运算器设计实验/dlp_ex_student/sim/wave_matrix_vector.vcd
$version Generated by VerilatedVcd $end
$timescale 1ps $end
 $scope module TOP $end
  $var wire 1 _ clk $end
  $var wire 1 ` reset $end
  $var wire 1 a enable $end
  $var wire 16 b activations[0] [15:0] $end
  $var wire 16 c activations[1] [15:0] $end
  $var wire 16 d activations[2] [15:0] $end
  $var wire 16 e activations[3] [15:0] $end
  $var wire 16 f weights[0][0] [15:0] $end
  $var wire 16 g weights[0][1] [15:0] $end
  $var wire 16 h weights[0][2] [15:0] $end
  $var wire 16 i weights[0][3] [15:0] $end
  $var wire 16 j weights[1][0] [15:0] $end
  $var wire 16 k weights[1][1] [15:0] $end
  $var wire 16 l weights[1][2] [15:0] $end
  $var wire 16 m weights[1][3] [15:0] $end
  $var wire 16 n weights[2][0] [15:0] $end
  $var wire 16 o weights[2][1] [15:0] $end
  $var wire 16 p weights[2][2] [15:0] $end
  $var wire 16 q weights[2][3] [15:0] $end
  $var wire 16 r weights[3][0] [15:0] $end
  $var wire 16 s weights[3][1] [15:0] $end
  $var wire 16 t weights[3][2] [15:0] $end
  $var wire 16 u weights[3][3] [15:0] $end
  $var wire 32 v results[0] [31:0] $end
  $var wire 32 w results[1] [31:0] $end
  $var wire 32 x results[2] [31:0] $end
  $var wire 32 y results[3] [31:0] $end
  $scope module matrix_vector_mult_4x4x16 $end
   $var wire 1 _ clk $end
   $var wire 1 ` reset $end
   $var wire 1 a enable $end
   $var wire 16 b activations[0] [15:0] $end
   $var wire 16 c activations[1] [15:0] $end
   $var wire 16 d activations[2] [15:0] $end
   $var wire 16 e activations[3] [15:0] $end
   $var wire 16 f weights[0][0] [15:0] $end
   $var wire 16 g weights[0][1] [15:0] $end
   $var wire 16 h weights[0][2] [15:0] $end
   $var wire 16 i weights[0][3] [15:0] $end
   $var wire 16 j weights[1][0] [15:0] $end
   $var wire 16 k weights[1][1] [15:0] $end
   $var wire 16 l weights[1][2] [15:0] $end
   $var wire 16 m weights[1][3] [15:0] $end
   $var wire 16 n weights[2][0] [15:0] $end
   $var wire 16 o weights[2][1] [15:0] $end
   $var wire 16 p weights[2][2] [15:0] $end
   $var wire 16 q weights[2][3] [15:0] $end
   $var wire 16 r weights[3][0] [15:0] $end
   $var wire 16 s weights[3][1] [15:0] $end
   $var wire 16 t weights[3][2] [15:0] $end
   $var wire 16 u weights[3][3] [15:0] $end
   $var wire 32 v results[0] [31:0] $end
   $var wire 32 w results[1] [31:0] $end
   $var wire 32 x results[2] [31:0] $end
   $var wire 32 y results[3] [31:0] $end
   $scope module ipu0 $end
    $var wire 1 _ clk $end
    $var wire 1 ` reset $end
    $var wire 1 a enable $end
    $var wire 16 b activations[0] [15:0] $end
    $var wire 16 c activations[1] [15:0] $end
    $var wire 16 d activations[2] [15:0] $end
    $var wire 16 e activations[3] [15:0] $end
    $var wire 16 # weights[0] [15:0] $end
    $var wire 16 $ weights[1] [15:0] $end
    $var wire 16 % weights[2] [15:0] $end
    $var wire 16 & weights[3] [15:0] $end
    $var wire 32 3 result [31:0] $end
    $var wire 16 4 activations_reg[0] [15:0] $end
    $var wire 16 5 activations_reg[1] [15:0] $end
    $var wire 16 6 activations_reg[2] [15:0] $end
    $var wire 16 7 activations_reg[3] [15:0] $end
    $var wire 16 8 weights_reg[0] [15:0] $end
    $var wire 16 9 weights_reg[1] [15:0] $end
    $var wire 16 : weights_reg[2] [15:0] $end
    $var wire 16 ; weights_reg[3] [15:0] $end
    $var wire 32 < dot_product [31:0] $end
    $var wire 32 = i [31:0] $end
   $upscope $end
   $scope module ipu1 $end
    $var wire 1 _ clk $end
    $var wire 1 ` reset $end
    $var wire 1 a enable $end
    $var wire 16 b activations[0] [15:0] $end
    $var wire 16 c activations[1] [15:0] $end
    $var wire 16 d activations[2] [15:0] $end
    $var wire 16 e activations[3] [15:0] $end
    $var wire 16 ' weights[0] [15:0] $end
    $var wire 16 ( weights[1] [15:0] $end
    $var wire 16 ) weights[2] [15:0] $end
    $var wire 16 * weights[3] [15:0] $end
    $var wire 32 > result [31:0] $end
    $var wire 16 ? activations_reg[0] [15:0] $end
    $var wire 16 @ activations_reg[1] [15:0] $end
    $var wire 16 A activations_reg[2] [15:0] $end
    $var wire 16 B activations_reg[3] [15:0] $end
    $var wire 16 C weights_reg[0] [15:0] $end
    $var wire 16 D weights_reg[1] [15:0] $end
    $var wire 16 E weights_reg[2] [15:0] $end
    $var wire 16 F weights_reg[3] [15:0] $end
    $var wire 32 G dot_product [31:0] $end
    $var wire 32 H i [31:0] $end
   $upscope $end
   $scope module ipu2 $end
    $var wire 1 _ clk $end
    $var wire 1 ` reset $end
    $var wire 1 a enable $end
    $var wire 16 b activations[0] [15:0] $end
    $var wire 16 c activations[1] [15:0] $end
    $var wire 16 d activations[2] [15:0] $end
    $var wire 16 e activations[3] [15:0] $end
    $var wire 16 + weights[0] [15:0] $end
    $var wire 16 , weights[1] [15:0] $end
    $var wire 16 - weights[2] [15:0] $end
    $var wire 16 . weights[3] [15:0] $end
    $var wire 32 I result [31:0] $end
    $var wire 16 J activations_reg[0] [15:0] $end
    $var wire 16 K activations_reg[1] [15:0] $end
    $var wire 16 L activations_reg[2] [15:0] $end
    $var wire 16 M activations_reg[3] [15:0] $end
    $var wire 16 N weights_reg[0] [15:0] $end
    $var wire 16 O weights_reg[1] [15:0] $end
    $var wire 16 P weights_reg[2] [15:0] $end
    $var wire 16 Q weights_reg[3] [15:0] $end
    $var wire 32 R dot_product [31:0] $end
    $var wire 32 S i [31:0] $end
   $upscope $end
   $scope module ipu3 $end
    $var wire 1 _ clk $end
    $var wire 1 ` reset $end
    $var wire 1 a enable $end
    $var wire 16 b activations[0] [15:0] $end
    $var wire 16 c activations[1] [15:0] $end
    $var wire 16 d activations[2] [15:0] $end
    $var wire 16 e activations[3] [15:0] $end
    $var wire 16 / weights[0] [15:0] $end
    $var wire 16 0 weights[1] [15:0] $end
    $var wire 16 1 weights[2] [15:0] $end
    $var wire 16 2 weights[3] [15:0] $end
    $var wire 32 T result [31:0] $end
    $var wire 16 U activations_reg[0] [15:0] $end
    $var wire 16 V activations_reg[1] [15:0] $end
    $var wire 16 W activations_reg[2] [15:0] $end
    $var wire 16 X activations_reg[3] [15:0] $end
    $var wire 16 Y weights_reg[0] [15:0] $end
    $var wire 16 Z weights_reg[1] [15:0] $end
    $var wire 16 [ weights_reg[2] [15:0] $end
    $var wire 16 \ weights_reg[3] [15:0] $end
    $var wire 32 ] dot_product [31:0] $end
    $var wire 32 ^ i [31:0] $end
   $upscope $end
  $upscope $end
 $upscope $end
$enddefinitions $end


#0
b0000000000000000 #
b0000000000000000 $
b0000000000000000 %
b0000000000000000 &
b0000000000000000 '
b0000000000000000 (
b0000000000000000 )
b0000000000000000 *
b0000000000000000 +
b0000000000000000 ,
b0000000000000000 -
b0000000000000000 .
b0000000000000000 /
b0000000000000000 0
b0000000000000000 1
b0000000000000000 2
b00000000000000000000000000000000 3
b0000000000000000 4
b0000000000000000 5
b0000000000000000 6
b0000000000000000 7
b0000000000000000 8
b0000000000000000 9
b0000000000000000 :
b0000000000000000 ;
b00000000000000000000000000000000 <
b00000000000000000000000000000000 =
b00000000000000000000000000000000 >
b0000000000000000 ?
b0000000000000000 @
b0000000000000000 A
b0000000000000000 B
b0000000000000000 C
b0000000000000000 D
b0000000000000000 E
b0000000000000000 F
b00000000000000000000000000000000 G
b00000000000000000000000000000000 H
b00000000000000000000000000000000 I
b0000000000000000 J
b0000000000000000 K
b0000000000000000 L
b0000000000000000 M
b0000000000000000 N
b0000000000000000 O
b0000000000000000 P
b0000000000000000 Q
b00000000000000000000000000000000 R
b00000000000000000000000000000000 S
b00000000000000000000000000000000 T
b0000000000000000 U
b0000000000000000 V
b0000000000000000 W
b0000000000000000 X
b0000000000000000 Y
b0000000000000000 Z
b0000000000000000 [
b0000000000000000 \
b00000000000000000000000000000000 ]
b00000000000000000000000000000000 ^
1_
1`
0a
b0000000000000000 b
b0000000000000000 c
b0000000000000000 d
b0000000000000000 e
b0000000000000000 f
b0000000000000000 g
b0000000000000000 h
b0000000000000000 i
b0000000000000000 j
b0000000000000000 k
b0000000000000000 l
b0000000000000000 m
b0000000000000000 n
b0000000000000000 o
b0000000000000000 p
b0000000000000000 q
b0000000000000000 r
b0000000000000000 s
b0000000000000000 t
b0000000000000000 u
b00000000000000000000000000000000 v
b00000000000000000000000000000000 w
b00000000000000000000000000000000 x
b00000000000000000000000000000000 y
#1
0_
#2
b00000000000000000000000000000100 =
b00000000000000000000000000000100 H
b00000000000000000000000000000100 S
b00000000000000000000000000000100 ^
1_
#3
0_
#4
1_
#5
0_
0`
#6
1_
#7
0_
#8
1_
#9
b0000000000000001 #
b0000000000000001 (
b0000000000000001 -
b0000000000000001 2
0_
b0000000000000001 b
b0000000000000010 c
b0000000000000011 d
b0000000000000100 e
b0000000000000001 f
b0000000000000001 k
b0000000000000001 p
b0000000000000001 u
#10
1_
#11
0_
1a
#12
b0000000000000001 4
b0000000000000010 5
b0000000000000011 6
b0000000000000100 7
b0000000000000001 8
b00000000000000000000000000000001 <
b0000000000000001 ?
b0000000000000010 @
b0000000000000011 A
b0000000000000100 B
b0000000000000001 D
b00000000000000000000000000000010 G
b0000000000000001 J
b0000000000000010 K
b0000000000000011 L
b0000000000000100 M
b0000000000000001 P
b00000000000000000000000000000011 R
b0000000000000001 U
b0000000000000010 V
b0000000000000011 W
b0000000000000100 X
b0000000000000001 \
b00000000000000000000000000000100 ]
1_
#13
0_
#14
b00000000000000000000000000000001 3
b00000000000000000000000000000010 >
b00000000000000000000000000000011 I
b00000000000000000000000000000100 T
1_
b00000000000000000000000000000001 v
b00000000000000000000000000000010 w
b00000000000000000000000000000011 x
b00000000000000000000000000000100 y
#15
0_
#16
1_
#17
0_
#18
1_
#19
0_
0a
