第六七章-深度学习处理器运算器设计实验/dlp_ex_student/src/inner_product_4x16.v
module inner_product_4x16 (
    input wire clk,
    input wire reset,
    input wire enable,
    input wire signed [15:0] activations [0:3],
    input wire signed [15:0] weights [0:3],
    output reg signed [31:0] result
);
    // 输入寄存器
    reg signed [15:0] activations_reg [0:3];
    reg signed [15:0] weights_reg [0:3];
    
    // 组合逻辑部分
    wire signed [31:0] dot_product = 
        (activations_reg[0] * weights_reg[0]) +
        (activations_reg[1] * weights_reg[1]) +
        (activations_reg[2] * weights_reg[2]) +
        (activations_reg[3] * weights_reg[3]);
    
    // 寄存器更新逻辑
    integer i;
    always @(posedge clk) begin
        if (reset) begin
            for (i = 0; i < 4; i = i + 1) begin
                activations_reg[i] <= 16'd0;
                weights_reg[i] <= 16'd0;
            end
            result <= 32'd0;
        end else if (enable) begin
            for (i = 0; i < 4; i = i + 1) begin
                activations_reg[i] <= activations[i];
                weights_reg[i] <= weights[i];
            end
            result <= dot_product;
        end
    end
endmodule

第六七章-深度学习处理器运算器设计实验/dlp_ex_student/sim/wave_inner.vcd
$version Generated by VerilatedVcd $end
$timescale 1ps $end
 $scope module TOP $end
  $var wire 1 - clk $end
  $var wire 1 . reset $end
  $var wire 1 / enable $end
  $var wire 16 0 activations[0] [15:0] $end
  $var wire 16 1 activations[1] [15:0] $end
  $var wire 16 2 activations[2] [15:0] $end
  $var wire 16 3 activations[3] [15:0] $end
  $var wire 16 4 weights[0] [15:0] $end
  $var wire 16 5 weights[1] [15:0] $end
  $var wire 16 6 weights[2] [15:0] $end
  $var wire 16 7 weights[3] [15:0] $end
  $var wire 32 8 result [31:0] $end
  $scope module inner_product_4x16 $end
   $var wire 1 - clk $end
   $var wire 1 . reset $end
   $var wire 1 / enable $end
   $var wire 16 0 activations[0] [15:0] $end
   $var wire 16 1 activations[1] [15:0] $end
   $var wire 16 2 activations[2] [15:0] $end
   $var wire 16 3 activations[3] [15:0] $end
   $var wire 16 4 weights[0] [15:0] $end
   $var wire 16 5 weights[1] [15:0] $end
   $var wire 16 6 weights[2] [15:0] $end
   $var wire 16 7 weights[3] [15:0] $end
   $var wire 32 8 result [31:0] $end
   $var wire 16 # activations_reg[0] [15:0] $end
   $var wire 16 $ activations_reg[1] [15:0] $end
   $var wire 16 % activations_reg[2] [15:0] $end
   $var wire 16 & activations_reg[3] [15:0] $end
   $var wire 16 ' weights_reg[0] [15:0] $end
   $var wire 16 ( weights_reg[1] [15:0] $end
   $var wire 16 ) weights_reg[2] [15:0] $end
   $var wire 16 * weights_reg[3] [15:0] $end
   $var wire 32 + dot_product [31:0] $end
   $var wire 32 , i [31:0] $end
  $upscope $end
 $upscope $end
$enddefinitions $end


#0
b0000000000000000 #
b0000000000000000 $
b0000000000000000 %
b0000000000000000 &
b0000000000000000 '
b0000000000000000 (
b0000000000000000 )
b0000000000000000 *
b00000000000000000000000000000000 +
b00000000000000000000000000000000 ,
1-
1.
0/
b0000000000000000 0
b0000000000000000 1
b0000000000000000 2
b0000000000000000 3
b0000000000000000 4
b0000000000000000 5
b0000000000000000 6
b0000000000000000 7
b00000000000000000000000000000000 8
#1
0-
#2
b00000000000000000000000000000100 ,
1-
#3
0-
#4
1-
#5
0-
0.
#6
1-
#7
0-
#8
1-
#9
0-
b0000000000000001 0
b0000000000000010 1
b0000000000000011 2
b0000000000000100 3
b0000000000000001 4
#10
1-
#11
0-
1/
#12
b0000000000000001 #
b0000000000000010 $
b0000000000000011 %
b0000000000000100 &
b0000000000000001 '
b00000000000000000000000000000001 +
1-
#13
0-
#14
1-
b00000000000000000000000000000001 8
#15
0-
0/
